{"cameraMode":{"drawMode":0,"name":"Shaded","section":"Shading Mode"},"sceneLighting":true,"audioPlay":false,"sceneViewState":{"m_AlwaysRefresh":false,"showFog":true,"showSkybox":true,"showFlares":true,"showImageEffects":true,"showParticleSystems":true,"showVisualEffectGraphs":true,"m_FxEnabled":true},"in2DMode":false,"pivot":{"x":5.274341106414795,"y":140.34805297851563,"z":12.54866886138916},"rotation":{"x":-0.654617965221405,"y":-0.026719797402620317,"z":0.02320973388850689,"w":-0.754994809627533},"size":72.2841796875,"orthographic":false}